{
	"web": {
		"client_id":"652748545377-pdnt9kd138hcustuofa1duqqrk7iscuu.apps.googleusercontent.com",
		"project_id":"apartment-inventory",
		"auth_uri":"https://accounts.google.com/o/oauth2/auth",
		"token_uri":"https://accounts.google.com/o/oauth2/token",
		"auth_provider_x509_cert_url":"https://www.googleapis.com/oauth2/v1/certs",
		"client_secret":"aQSWTsGHaDH-W7M_XgVOz81A",
		"redirect_uris":[
			"http://127.0.0.1:5000/gconnect",
			"http://localhost:5000/gconnect",
			"http://127.0.0.1:5000/login",
			"http://localhost:5000/login"],
		"javascript_origins":[
			"http://127.0.0.1:5000",
			"http://localhost:5000"]
	}
}